myfunctions_echervenko/__init__.py
myfunctions_echervenko/math.py
myfunctions_echervenko-0.0.6.dist-info/METADATA
myfunctions_echervenko-0.0.6.dist-info/WHEEL
myfunctions_echervenko-0.0.6.dist-info/top_level.txt
myfunctions_echervenko-0.0.6.dist-info/RECORD
