Metadata-Version: 2.1
Name: myfunctions_echervenko
Version: 0.0.6
Summary: A description of your package
Home-page: https://github.com/echervenko
Author: Elena Chervenko
Author-email: chervenkoelena@gmail.com
License: MIT
Platform: UNKNOWN
Classifier: Programming Language :: Python :: 3
Classifier: License :: OSI Approved :: MIT License
Classifier: Operating System :: OS Independent
Requires-Python: >=3.6
